CHANGELOG.rst
CREDITS.rst
LICENSE.txt
MANIFEST.in
README.rst
pyproject.toml
requirements.txt
setup.py
l_thonny.egg-info/PKG-INFO
l_thonny.egg-info/SOURCES.txt
l_thonny.egg-info/dependency_links.txt
l_thonny.egg-info/entry_points.txt
l_thonny.egg-info/requires.txt
l_thonny.egg-info/top_level.txt
licenses/ECLIPSE-ICONS-LICENSE.txt
packaging/icons/thonny-128x128.png
packaging/icons/thonny-16x16.png
packaging/icons/thonny-192x192.png
packaging/icons/thonny-2.png
packaging/icons/thonny-22x22.png
packaging/icons/thonny-256x256.png
packaging/icons/thonny-32x32.png
packaging/icons/thonny-48x48.png
packaging/icons/thonny-64x64.png
packaging/linux/org.thonny.Thonny.appdata.xml
packaging/linux/org.thonny.Thonny.desktop
packaging/linux/thonny.1
thonny/VERSION
thonny/__init__.py
thonny/__main__.py
thonny/assistance.py
thonny/ast_utils.py
thonny/backend.py
thonny/base_file_browser.py
thonny/codeview.py
thonny/common.py
thonny/config.py
thonny/config_ui.py
thonny/custom_notebook.py
thonny/defaults.ini
thonny/editor_helpers.py
thonny/editors.py
thonny/exam.py
thonny/exam_details.py
thonny/export.py
thonny/file_tree.py
thonny/first_run.py
thonny/gridtable.py
thonny/homework_and_exam.py
thonny/jedi_utils.py
thonny/languages.py
thonny/login.py
thonny/memory.py
thonny/misc_utils.py
thonny/myHttp.py
thonny/mysql_sql.py
thonny/roughparse.py
thonny/rst_utils.py
thonny/running.py
thonny/shell.py
thonny/sqlite3_sql.py
thonny/terminal.py
thonny/test.py
thonny/time_select.py
thonny/tktextext.py
thonny/token_utils.py
thonny/udisks.py
thonny/ui_utils.py
thonny/video.py
thonny/work.py
thonny/workbench.py
thonny/workdlg.py
thonny/dbus/org.freedesktop.DBus.ObjectManager.xml
thonny/dbus/org.freedesktop.UDisks2.xml
thonny/locale/compile_mo.bat
thonny/locale/register_updates.py
thonny/locale/thonny.pot
thonny/locale/update_pot.bat
thonny/locale/ar_AR/LC_MESSAGES/thonny.mo
thonny/locale/ar_AR/LC_MESSAGES/thonny.po
thonny/locale/cs_CZ/LC_MESSAGES/thonny.mo
thonny/locale/cs_CZ/LC_MESSAGES/thonny.po
thonny/locale/de_DE/LC_MESSAGES/thonny.mo
thonny/locale/de_DE/LC_MESSAGES/thonny.po
thonny/locale/el_GR/LC_MESSAGES/thonny.mo
thonny/locale/el_GR/LC_MESSAGES/thonny.po
